xenodocs_mcp_server/__init__.py
xenodocs_mcp_server/server.py
xenodocs_mcp_server-0.1.4.dist-info/METADATA
xenodocs_mcp_server-0.1.4.dist-info/WHEEL
xenodocs_mcp_server-0.1.4.dist-info/entry_points.txt
xenodocs_mcp_server-0.1.4.dist-info/licenses/LICENSE
xenodocs_mcp_server-0.1.4.dist-info/RECORD
