Metadata-Version: 2.4
Name: xenodocs-mcp-server
Version: 0.1.4
Summary: MCP server for XenoDocs - Access up-to-date documentation for newly released packages using AI.
Project-URL: Homepage, https://xenodocs.com
Project-URL: Repository, https://github.com/Xenodocs/xenodocs-mcp-server
Project-URL: Issues, https://github.com/Xenodocs/xenodocs-mcp-server/issues
Author-email: Ravi Kumawat <ravi@evolvue.ai>, Mahendra Kharra <mahendra@evolvue.ai>, Mayank Aggarwal <mayank@evolvue.ai>, Krish Naik <krishnaik@xenodocs.com>, Sourangshu Pal <sourangshu@xenodocs.com>
License: MIT
License-File: LICENSE
Keywords: ai,copilot,documentation,mcp,vscode,xenodocs,xenodocs-mcp-server
Classifier: Development Status :: 4 - Beta
Classifier: Intended Audience :: Developers
Classifier: License :: OSI Approved :: MIT License
Classifier: Programming Language :: Python :: 3
Classifier: Programming Language :: Python :: 3.10
Classifier: Programming Language :: Python :: 3.11
Classifier: Programming Language :: Python :: 3.12
Requires-Python: >=3.10
Requires-Dist: fastmcp>=0.2.0
Requires-Dist: httpx>=0.27.0
Requires-Dist: python-dotenv>=1.0.0
